{"Airport": {"Code": "MDW", "Name": "Chicago, IL: Chicago Midway International"}, "Time": {"Label": "2012/01", "Month": 1, "Month Name": "January", "Year": 2012}, "Statistics": {"# of Delays": {"Carrier": 191, "Late Aircraft": 259, "National Aviation System": 159, "Security": 4, "Weather": 69}, "Carriers": {"Names": "Delta Air Lines Inc.,Frontier Airlines Inc.,AirTran Airways Corporation,Southwest Airlines Co.", "Total": 4}, "Flights": {"Cancelled": 145, "Delayed": 682, "Diverted": 27, "On Time": 5674, "Total": 6528}, "Minutes Delayed": {"Carrier": 9513, "Late Aircraft": 13388, "National Aviation System": 6827, "Security": 94, "Total": 40275, "Weather": 10453}}}
