{"Airport": {"Code": "DEN", "Name": "Denver, CO: Denver International"}, "Time": {"Label": "2012/02", "Month": 2, "Month Name": "Febuary", "Year": 2012}, "Statistics": {"# of Delays": {"Carrier": 637, "Late Aircraft": 955, "National Aviation System": 1076, "Security": 2, "Weather": 121}, "Carriers": {"Names": "American Airlines Inc.,Alaska Airlines Inc.,JetBlue Airways,Delta Air Lines Inc.,ExpressJet Airlines Inc.,Frontier Airlines Inc.,AirTran Airways Corporation,American Eagle Airlines Inc.,SkyWest Airlines Inc.,United Air Lines Inc.,US Airways Inc.,Southwest Airlines Co.", "Total": 12}, "Flights": {"Cancelled": 433, "Delayed": 2792, "Diverted": 21, "On Time": 14931, "Total": 18177}, "Minutes Delayed": {"Carrier": 37696, "Late Aircraft": 54577, "National Aviation System": 47945, "Security": 54, "Total": 149007, "Weather": 8735}}}
