{"Airport": {"Code": "CLT", "Name": "Charlotte, NC: Charlotte Douglas International"}, "Time": {"Label": "2012/04", "Month": 4, "Month Name": "April", "Year": 2012}, "Statistics": {"# of Delays": {"Carrier": 301, "Late Aircraft": 348, "National Aviation System": 394, "Security": 4, "Weather": 20}, "Carriers": {"Names": "American Airlines Inc.,JetBlue Airways,Delta Air Lines Inc.,ExpressJet Airlines Inc.,AirTran Airways Corporation,American Eagle Airlines Inc.,SkyWest Airlines Inc.,United Air Lines Inc.,US Airways Inc.,Mesa Airlines Inc.", "Total": 10}, "Flights": {"Cancelled": 67, "Delayed": 1067, "Diverted": 4, "On Time": 10394, "Total": 11532}, "Minutes Delayed": {"Carrier": 17381, "Late Aircraft": 17859, "National Aviation System": 11327, "Security": 99, "Total": 48080, "Weather": 1414}}}
