{"Airport": {"Code": "LAX", "Name": "Los Angeles, CA: Los Angeles International"}, "Time": {"Label": "2012/11", "Month": 11, "Month Name": "November", "Year": 2012}, "Statistics": {"# of Delays": {"Carrier": 751, "Late Aircraft": 1154, "National Aviation System": 759, "Security": 6, "Weather": 46}, "Carriers": {"Names": "American Airlines Inc.,Alaska Airlines Inc.,JetBlue Airways,Delta Air Lines Inc.,Frontier Airlines Inc.,AirTran Airways Corporation,Hawaiian Airlines Inc.,American Eagle Airlines Inc.,SkyWest Airlines Inc.,United Air Lines Inc.,US Airways Inc.,Virgin America,Southwest Airlines Co.", "Total": 13}, "Flights": {"Cancelled": 220, "Delayed": 2716, "Diverted": 38, "On Time": 14594, "Total": 17568}, "Minutes Delayed": {"Carrier": 39271, "Late Aircraft": 72008, "National Aviation System": 23365, "Security": 277, "Total": 138202, "Weather": 3281}}}
