{"Airport": {"Code": "SLC", "Name": "Salt Lake City, UT: Salt Lake City International"}, "Time": {"Label": "2013/01", "Month": 1, "Month Name": "January", "Year": 2013}, "Statistics": {"# of Delays": {"Carrier": 395, "Late Aircraft": 620, "National Aviation System": 603, "Security": 5, "Weather": 64}, "Carriers": {"Names": "Pinnacle Airlines Inc.,American Airlines Inc.,JetBlue Airways,Delta Air Lines Inc.,ExpressJet Airlines Inc.,Frontier Airlines Inc.,American Eagle Airlines Inc.,SkyWest Airlines Inc.,United Air Lines Inc.,US Airways Inc.,Southwest Airlines Co.", "Total": 11}, "Flights": {"Cancelled": 238, "Delayed": 1686, "Diverted": 116, "On Time": 7018, "Total": 9058}, "Minutes Delayed": {"Carrier": 26852, "Late Aircraft": 42118, "National Aviation System": 25138, "Security": 117, "Total": 101104, "Weather": 6879}}}
