{"Airport": {"Code": "MCO", "Name": "Orlando, FL: Orlando International"}, "Time": {"Label": "2013/02", "Month": 2, "Month Name": "Febuary", "Year": 2013}, "Statistics": {"# of Delays": {"Carrier": 508, "Late Aircraft": 462, "National Aviation System": 654, "Security": 3, "Weather": 36}, "Carriers": {"Names": "Pinnacle Airlines Inc.,American Airlines Inc.,Alaska Airlines Inc.,JetBlue Airways,Delta Air Lines Inc.,ExpressJet Airlines Inc.,Frontier Airlines Inc.,AirTran Airways Corporation,United Air Lines Inc.,US Airways Inc.,Virgin America,Southwest Airlines Co.", "Total": 12}, "Flights": {"Cancelled": 129, "Delayed": 1663, "Diverted": 6, "On Time": 7230, "Total": 9028}, "Minutes Delayed": {"Carrier": 28049, "Late Aircraft": 28630, "National Aviation System": 20298, "Security": 99, "Total": 79293, "Weather": 2217}}}
