{"Airport": {"Code": "LAS", "Name": "Las Vegas, NV: McCarran International"}, "Time": {"Label": "2013/03", "Month": 3, "Month Name": "March", "Year": 2013}, "Statistics": {"# of Delays": {"Carrier": 576, "Late Aircraft": 846, "National Aviation System": 401, "Security": 5, "Weather": 28}, "Carriers": {"Names": "American Airlines Inc.,Alaska Airlines Inc.,JetBlue Airways,Delta Air Lines Inc.,Frontier Airlines Inc.,AirTran Airways Corporation,Hawaiian Airlines Inc.,SkyWest Airlines Inc.,United Air Lines Inc.,US Airways Inc.,Virgin America,Southwest Airlines Co.", "Total": 12}, "Flights": {"Cancelled": 48, "Delayed": 1857, "Diverted": 20, "On Time": 9915, "Total": 11840}, "Minutes Delayed": {"Carrier": 29926, "Late Aircraft": 44608, "National Aviation System": 13466, "Security": 223, "Total": 90800, "Weather": 2577}}}
