{"Airport": {"Code": "BOS", "Name": "Boston, MA: Logan International"}, "Time": {"Label": "2013/10", "Month": 10, "Month Name": "October", "Year": 2013}, "Statistics": {"# of Delays": {"Carrier": 386, "Late Aircraft": 401, "National Aviation System": 347, "Security": 1, "Weather": 14}, "Carriers": {"Names": "Endeavor Air Inc.,American Airlines Inc.,Alaska Airlines Inc.,JetBlue Airways,Delta Air Lines Inc.,ExpressJet Airlines Inc.,AirTran Airways Corporation,SkyWest Airlines Inc.,United Air Lines Inc.,US Airways Inc.,Virgin America,Southwest Airlines Co.,Mesa Airlines Inc.", "Total": 13}, "Flights": {"Cancelled": 31, "Delayed": 1148, "Diverted": 6, "On Time": 8517, "Total": 9702}, "Minutes Delayed": {"Carrier": 19001, "Late Aircraft": 23178, "National Aviation System": 11051, "Security": 47, "Total": 54033, "Weather": 756}}}
