{"Airport": {"Code": "TPA", "Name": "Tampa, FL: Tampa International"}, "Time": {"Label": "2014/05", "Month": 5, "Month Name": "May", "Year": 2014}, "Statistics": {"# of Delays": {"Carrier": 377, "Late Aircraft": 430, "National Aviation System": 330, "Security": 1, "Weather": 31}, "Carriers": {"Names": "American Airlines Inc.,JetBlue Airways,Delta Air Lines Inc.,ExpressJet Airlines Inc.,Frontier Airlines Inc.,AirTran Airways Corporation,Envoy Air,SkyWest Airlines Inc.,United Air Lines Inc.,US Airways Inc.,Southwest Airlines Co.", "Total": 11}, "Flights": {"Cancelled": 37, "Delayed": 1168, "Diverted": 53, "On Time": 4347, "Total": 5605}, "Minutes Delayed": {"Carrier": 20047, "Late Aircraft": 27285, "National Aviation System": 13414, "Security": 17, "Total": 63563, "Weather": 2800}}}
