{"Airport": {"Code": "IAD", "Name": "Washington, DC: Washington Dulles International"}, "Time": {"Label": "2014/10", "Month": 10, "Month Name": "October", "Year": 2014}, "Statistics": {"# of Delays": {"Carrier": 264, "Late Aircraft": 442, "National Aviation System": 338, "Security": 1, "Weather": 18}, "Carriers": {"Names": "American Airlines Inc.,JetBlue Airways,Delta Air Lines Inc.,ExpressJet Airlines Inc.,Frontier Airlines Inc.,SkyWest Airlines Inc.,United Air Lines Inc.,Virgin America,Southwest Airlines Co.", "Total": 9}, "Flights": {"Cancelled": 27, "Delayed": 1064, "Diverted": 4, "On Time": 3960, "Total": 5055}, "Minutes Delayed": {"Carrier": 13878, "Late Aircraft": 30071, "National Aviation System": 14418, "Security": 13, "Total": 59562, "Weather": 1182}}}
