{"Airport": {"Code": "JFK", "Name": "New York, NY: John F. Kennedy International"}, "Time": {"Label": "2014/10", "Month": 10, "Month Name": "October", "Year": 2014}, "Statistics": {"# of Delays": {"Carrier": 366, "Late Aircraft": 441, "National Aviation System": 944, "Security": 1, "Weather": 35}, "Carriers": {"Names": "American Airlines Inc.,JetBlue Airways,Delta Air Lines Inc.,ExpressJet Airlines Inc.,Hawaiian Airlines Inc.,Envoy Air,United Air Lines Inc.,US Airways Inc.,Virgin America", "Total": 9}, "Flights": {"Cancelled": 30, "Delayed": 1789, "Diverted": 22, "On Time": 6795, "Total": 8636}, "Minutes Delayed": {"Carrier": 22378, "Late Aircraft": 25834, "National Aviation System": 42206, "Security": 26, "Total": 92703, "Weather": 2259}}}
