{"Airport": {"Code": "MSP", "Name": "Minneapolis, MN: Minneapolis-St Paul International"}, "Time": {"Label": "2014/11", "Month": 11, "Month Name": "November", "Year": 2014}, "Statistics": {"# of Delays": {"Carrier": 401, "Late Aircraft": 530, "National Aviation System": 601, "Security": 3, "Weather": 46}, "Carriers": {"Names": "American Airlines Inc.,Alaska Airlines Inc.,Delta Air Lines Inc.,ExpressJet Airlines Inc.,Frontier Airlines Inc.,AirTran Airways Corporation,Envoy Air,SkyWest Airlines Inc.,United Air Lines Inc.,US Airways Inc.,Southwest Airlines Co.", "Total": 11}, "Flights": {"Cancelled": 109, "Delayed": 1581, "Diverted": 12, "On Time": 6578, "Total": 8280}, "Minutes Delayed": {"Carrier": 29137, "Late Aircraft": 31799, "National Aviation System": 27010, "Security": 44, "Total": 91869, "Weather": 3879}}}
