{"Airport": {"Code": "MSP", "Name": "Minneapolis, MN: Minneapolis-St Paul International"}, "Time": {"Label": "2015/04", "Month": 4, "Month Name": "April", "Year": 2015}, "Statistics": {"# of Delays": {"Carrier": 440, "Late Aircraft": 455, "National Aviation System": 592, "Security": 1, "Weather": 41}, "Carriers": {"Names": "American Airlines Inc.,Alaska Airlines Inc.,Delta Air Lines Inc.,ExpressJet Airlines Inc.,Frontier Airlines Inc.,Spirit Air Lines,SkyWest Airlines Inc.,United Air Lines Inc.,US Airways Inc.,Southwest Airlines Co.", "Total": 10}, "Flights": {"Cancelled": 38, "Delayed": 1526, "Diverted": 23, "On Time": 8426, "Total": 10013}, "Minutes Delayed": {"Carrier": 30957, "Late Aircraft": 26259, "National Aviation System": 18586, "Security": 17, "Total": 79842, "Weather": 4023}}}
