{"Airport": {"Code": "SAN", "Name": "San Diego, CA: San Diego International"}, "Time": {"Label": "2015/07", "Month": 7, "Month Name": "July", "Year": 2015}, "Statistics": {"# of Delays": {"Carrier": 518, "Late Aircraft": 700, "National Aviation System": 315, "Security": 1, "Weather": 32}, "Carriers": {"Names": "American Airlines Inc.,Alaska Airlines Inc.,JetBlue Airways,Delta Air Lines Inc.,Frontier Airlines Inc.,Hawaiian Airlines Inc.,Spirit Air Lines,SkyWest Airlines Inc.,United Air Lines Inc.,Virgin America,Southwest Airlines Co.", "Total": 11}, "Flights": {"Cancelled": 57, "Delayed": 1564, "Diverted": 25, "On Time": 5385, "Total": 7031}, "Minutes Delayed": {"Carrier": 28411, "Late Aircraft": 42242, "National Aviation System": 11663, "Security": 33, "Total": 84314, "Weather": 1965}}}
