{"Airport": {"Code": "IAD", "Name": "Washington, DC: Washington Dulles International"}, "Time": {"Label": "2015/12", "Month": 12, "Month Name": "December", "Year": 2015}, "Statistics": {"# of Delays": {"Carrier": 182, "Late Aircraft": 183, "National Aviation System": 61, "Security": 0, "Weather": 17}, "Carriers": {"Names": "American Airlines Inc.,Alaska Airlines Inc.,JetBlue Airways,Delta Air Lines Inc.,ExpressJet Airlines Inc.,Frontier Airlines Inc.,SkyWest Airlines Inc.,United Air Lines Inc.,Virgin America,Southwest Airlines Co.", "Total": 10}, "Flights": {"Cancelled": 28, "Delayed": 443, "Diverted": 3, "On Time": 2325, "Total": 2799}, "Minutes Delayed": {"Carrier": 11075, "Late Aircraft": 15438, "National Aviation System": 2826, "Security": 0, "Total": 31164, "Weather": 1825}}}
